LICENSE
onelongcyclelr/__init__.py
onelongcyclelr/onelongcyclelr.py
onelongcyclelr-0.1.2.dist-info/LICENSE
onelongcyclelr-0.1.2.dist-info/WHEEL
onelongcyclelr-0.1.2.dist-info/METADATA
onelongcyclelr-0.1.2.dist-info/RECORD
