Metadata-Version: 2.1
Name: onelongcyclelr
Version: 0.1.2
Summary: An adaptation of pytorch OneCycleLR that doesn't crash when max steps is reached
Home-page: https://github.com/abcamiletto/onelongcyclelr
Author: Andrea Boscolo Camiletto
Author-email: abcamiletto@gmail.com
Requires-Python: >=3.7,<4.0
Classifier: Programming Language :: Python :: 3
Classifier: Programming Language :: Python :: 3.10
Classifier: Programming Language :: Python :: 3.7
Classifier: Programming Language :: Python :: 3.8
Classifier: Programming Language :: Python :: 3.9
Requires-Dist: torch (>=1.0.0,<2.0.0)
Project-URL: Repository, https://github.com/abcamiletto/onelongcyclelr
